odoo/addons/web_search_with_and/README.rst
odoo/addons/web_search_with_and/__init__.py
odoo/addons/web_search_with_and/__manifest__.py
odoo/addons/web_search_with_and/data/data.xml
odoo/addons/web_search_with_and/i18n/ca.po
odoo/addons/web_search_with_and/i18n/es.po
odoo/addons/web_search_with_and/i18n/pt.po
odoo/addons/web_search_with_and/i18n/pt_BR.po
odoo/addons/web_search_with_and/i18n/web_search_with_and.pot
odoo/addons/web_search_with_and/readme/CONTRIBUTORS.rst
odoo/addons/web_search_with_and/readme/DESCRIPTION.rst
odoo/addons/web_search_with_and/readme/USAGE.rst
odoo/addons/web_search_with_and/static/description/icon.png
odoo/addons/web_search_with_and/static/description/index.html
odoo/addons/web_search_with_and/static/src/js/search.js
odoo12_addon_web_search_with_and-12.0.1.0.0.99.dev10.dist-info/METADATA
odoo12_addon_web_search_with_and-12.0.1.0.0.99.dev10.dist-info/WHEEL
odoo12_addon_web_search_with_and-12.0.1.0.0.99.dev10.dist-info/top_level.txt
odoo12_addon_web_search_with_and-12.0.1.0.0.99.dev10.dist-info/RECORD
